{
    "AWSTemplateFormatVersion" : "2010-09-09",
    "Parameters": {
        "GitSha": {
            "Type": "String",
            "Description": "GitSha to Deploy"
        },
        "MachineAuth": {
            "Type": "String",
            "Description": "The password for the default machine user"
        },
        "StackName": {
            "Type": "String",
            "Description": "Name of parent stack"
        },
        "PredictionId": {
            "Type": "String",
            "Description": "MLEnabler Prediction ID"
        },
        "TileEndpoint": {
            "Type": "String",
            "Description": "WMS Endpoint from which to pull chips"
        }
    },
    "Resources" : {
        "PredLogs": {
            "Type": "AWS::Logs::LogGroup",
            "Properties": {
                "LogGroupName": { "Fn::Join": [ "-", [
                    { "Ref": "StackName" },
                    { "Ref": "PredictionId" }
                ]]},
                "RetentionInDays": 7
            }
        },
        "PredInstanceProfile": {
            "Type": "AWS::IAM::InstanceProfile",
            "Properties": {
                "Path": "/",
                "Roles": [{ "Fn::ImportValue": { "Fn::Join": [ "-", [
                    { "Ref": "StackName" },
                    "exec-role-name"
                ]]}}]
            }
        },
        "PredContainerInstanceLaunch": {
            "Type": "AWS::AutoScaling::LaunchConfiguration",
            "DependsOn": "PredECSHostSecurityGroup",
            "Metadata": {
                "AWS::CloudFormation::Init": {
                    "config" : {
                        "commands": {
                            "01_add_instance_to_cluster": {
                                "command": { "Fn::Join": [ "", ["echo ECS_CLUSTER=", { "Fn::ImportValue": { "Fn::Join": [ "-", [ { "Ref": "StackName" }, "cluster" ]]}}, " >> /etc/ecs/ecs.config\n" ]] }
                            }
                        },
                        "files": {
                            "/etc/cfn/cfn-hup.conf": {
                                "content": {
                                    "Fn::Join": [ "", [
                                        "[main]\n",
                                        "stack=", { "Ref": "AWS::StackId" }, "\n",
                                        "region=", { "Ref": "AWS::Region" }, "\n"
                                    ]]
                                },
                                "mode": "000400",
                                "owner": "root",
                                "group": "root"
                            },
                            "/etc/cfn/hooks.d/cfn-auto-reloader.conf": {
                                "content": {
                                    "Fn::Join": [ "", [
                                        "[cfn-auto-reloader-hook]\n",
                                        "triggers=post.update\n",
                                        "path=Resources.PredContainerInstanceLaunch.Metadata.AWS::CloudFormation::Init\n",
                                        "action=/opt/aws/bin/cfn-init -v --stack ", { "Ref": "AWS::StackName" }, " --resource PredContainerInstanceLaunch --region ", { "Ref": "AWS::Region" }, "\n",
                                        "runas=root\n"
                                    ]]
                                }
                            }
                        },
                        "services": {
                            "sysvinit": {
                                "cfn-hup": {
                                    "enabled": "true",
                                    "ensureRunning": "true",
                                    "files": [
                                        "/etc/cfn/cfn-hup.conf",
                                        "/etc/cfn/hooks.d/cfn-auto-reloader.conf"
                                    ]
                                }
                            }
                        }
                    }
                }
            },
            "Properties": {
                "SecurityGroups": [{ "Ref": "PredECSHostSecurityGroup" }],
                "ImageId": { "Fn::FindInMap": [ "AWSRegionToAMI", { "Ref": "AWS::Region" }, "AMIID" ] },
                "InstanceType": "p3.2xlarge",
                "IamInstanceProfile": { "Ref": "PredInstanceProfile" },
                "BlockDeviceMappings": [{
                    "DeviceName": "/dev/xvdcz",
                    "Ebs": {
                        "DeleteOnTermination": true,
                        "VolumeSize": 100,
                        "VolumeType": "gp2"
                    }
                }],
                "UserData": {
                    "Fn::Base64": {
                        "Fn::Join": ["", [
                            "#!/bin/bash -xe\n",
                            "yum install -y aws-cfn-bootstrap\n",
                            "/opt/aws/bin/cfn-init -v --region ", { "Ref": "AWS::Region" }, " --stack ", { "Ref": "AWS::StackName" }, " --resource PredContainerInstanceLaunch\n",
                            "/opt/aws/bin/cfn-signal -e $? --region ", { "Ref": "AWS::Region" }, " --stack ", { "Ref": "AWS::StackName" }, " --resource PredECSAutoScalingGroup\n"
                        ]]
                    }
                }
            }
        },
        "PredECSAutoScalingGroup": {
            "Type": "AWS::AutoScaling::AutoScalingGroup",
            "CreationPolicy" : {
                "ResourceSignal" : {
                    "Timeout" : "PT10M",
                    "Count"   : "1"
                }
            },
            "UpdatePolicy": {
                "AutoScalingRollingUpdate": {
                    "MinInstancesInService": 0
                }
            },
            "Properties": {
                "AvailabilityZones": [
                    { "Fn::FindInMap": ["AWSRegion2AZ", { "Ref": "AWS::Region" }, "1"] },
                    { "Fn::FindInMap": ["AWSRegion2AZ", { "Ref": "AWS::Region" }, "2"] }
                ],
                "LaunchConfigurationName": { "Ref": "PredContainerInstanceLaunch" },
                "MinSize": 1,
                "MaxSize": 1,
                "DesiredCapacity": 1,
                "VPCZoneIdentifier": [
                    { "Fn::ImportValue": { "Fn::Join": [ "-", [ { "Ref": "StackName" }, "suba" ]]}},
                    { "Fn::ImportValue": { "Fn::Join": [ "-", [ { "Ref": "StackName" }, "subb" ]]}}
                ]
            }
        },
        "PredECSHostSecurityGroup": {
            "Type": "AWS::EC2::SecurityGroup",
            "Properties": {
                "VpcId": { "Fn::ImportValue": { "Fn::Join": [ "-", [
                    { "Ref": "StackName" },
                    "vpc"
                ]]}},
                "GroupDescription": "Access to the ECS hosts and the tasks/containers that run on them",
                "SecurityGroupIngress": []
            }
        },
        "PredService": {
            "Type": "AWS::ECS::Service",
            "DependsOn": [ "PredECSAutoScalingGroup" ],
            "Properties": {
                "ServiceName": { "Fn::Join": [ "-", [ { "Ref": "StackName" }, { "Ref": "PredictionId" }, "retrain" ]] },
                "Cluster": { "Fn::ImportValue": { "Fn::Join": [ "-", [ { "Ref": "StackName" }, "cluster" ]]}},
                "TaskDefinition": { "Ref": "PredTaskDefinition" },
                "DesiredCount": 1,
                "DeploymentConfiguration": {
                    "MaximumPercent": 100,
                    "MinimumHealthyPercent": 0
                }
            }
        },
        "PredTaskDefinition": {
            "Type": "AWS::ECS::TaskDefinition",
            "Properties": {
                "Family": { "Fn::Join": [ "-", [ { "Ref": "StackName" }, { "Ref": "PredictionId" }, "retrain" ]] },
                "Cpu": 8192,
                "Memory": 61401,
                "TaskRoleArn": { "Fn::ImportValue": { "Fn::Join": [ "-", [
                    { "Ref": "StackName" },
                    "task-role"
                ]]}},
                "ContainerDefinitions": [{
                    "Name": "pred-app",
                    "Essential": true,
                    "Image": { "Fn::Join" : [ "", [
                        { "Ref": "AWS::AccountId" },
                        ".dkr.ecr.",
                        { "Ref": "AWS::Region" },
                        ".amazonaws.com/",
                        { "Ref": "StackName" },
                        "-ecr:task-retrain-",
                        { "Ref": "GitSha" }
                    ] ] },
                    "PortMappings": [{
                        "ContainerPort": 8501
                    }],
                    "Environment": [],
                    "LogConfiguration": {
                        "LogDriver": "awslogs",
                        "Options": {
                            "awslogs-group": { "Fn::Join": [ "-", [
                                { "Ref": "StackName" },
                                { "Ref": "PredictionId" }
                            ]]},
                            "awslogs-region": { "Ref": "AWS::Region" }
                        }
                    }
                }]
            }
        }
    },
    "Mappings": {
        "AWSRegionToAMI": {
            "DOCS": { "LIST": "http://docs.aws.amazon.com/AmazonECS/latest/developerguide/ecs-optimized_AMI.html" },
            "us-east-1": { "AMIID": "ami-07eb64b216d4d3522" }
        },
        "AWSRegion2AZ": {
            "us-east-1": { "1": "us-east-1b", "2": "us-east-1c", "3": "us-east-1d", "4": "us-east-1e" },
            "us-west-1": { "1": "us-west-1b", "2": "us-west-1c" },
            "us-west-2": { "1": "us-west-2a", "2": "us-west-2b", "3": "us-west-2c" }
        }
    }
}
